pyvoro/__init__.py
pyvoro/voroplusplus.cp311-win_amd64.pyd
pyvoro_bazan-1.0.3.dist-info/LICENSE
pyvoro_bazan-1.0.3.dist-info/LICENSE.txt
pyvoro_bazan-1.0.3.dist-info/METADATA
pyvoro_bazan-1.0.3.dist-info/WHEEL
pyvoro_bazan-1.0.3.dist-info/top_level.txt
pyvoro_bazan-1.0.3.dist-info/RECORD
